<?xml version="1.0" encoding="utf-8"?>

<Module>
	<Name value="Party Screen Enhancements" />
	<Id value="PartyScreenEnhancements" />
	<Version value="v1.5.13" />
	<SingleplayerModule value="true" />
	<MultiplayerModule value="false" />
	<DependedModules>
		<DependedModule Id="Native" DependentVersion="e1.5.8"/>
		<DependedModule Id="SandBoxCore" DependentVersion="e1.5.8"/>
		<DependedModule Id="Sandbox" DependentVersion="e1.5.8"/>
		<DependedModule Id="CustomBattle" DependentVersion="e1.5.8"/>
		<DependedModule Id="StoryMode" DependentVersion="e1.5.8"/>
	</DependedModules>
	<SubModules>
		<SubModule>
			<Name value="PartyScreenEnhancements" />
			<DLLName value="PartyScreenEnhancements.dll" />
			<SubModuleClassType value="PartyScreenEnhancements.SubModule" />
			<Tags>
				<Tag key="DedicatedServerType" value="none" />
				<Tag key="IsNoRenderModeElement" value="false" />
			</Tags>
		</SubModule>
	</SubModules>

	<Xmls />
</Module>